README.md
setup.py
utcdatetime/__init__.py
utcdatetime/parse_datetime_string.py
utcdatetime/utc_timezone.py
utcdatetime/utcdatetime.py
utcdatetime.egg-info/PKG-INFO
utcdatetime.egg-info/SOURCES.txt
utcdatetime.egg-info/dependency_links.txt
utcdatetime.egg-info/top_level.txt
utcdatetime/tests/__init__.py
utcdatetime/tests/test_add_subtract_compare.py
utcdatetime/tests/test_astimezone.py
utcdatetime/tests/test_construct.py
utcdatetime/tests/test_date.py
utcdatetime/tests/test_from_datetime.py
utcdatetime/tests/test_now.py
utcdatetime/tests/test_parse_datetime_string.py
utcdatetime/tests/test_repr.py
utcdatetime/tests/test_str.py
utcdatetime/tests/test_time.py
utcdatetime/tests/test_utc_timezone.py