Metadata-Version: 1.1
Name: utcdatetime
Version: 0.0.7
Summary: Simple UTC datetimes using RFC3339 subset of ISO8601.
Home-page: https://github.com/paulfurley/python-utcdatetime
Author: Paul M Furley
Author-email: paul@paulfurley.com
License: UNKNOWN
Download-URL: https://github.com/paulfurley/python-utcdatetime/tarball/0.0.7
Platform: UNKNOWN
Classifier: Development Status :: 4 - Beta
Classifier: Environment :: Console
Classifier: License :: OSI Approved :: MIT License
Classifier: Natural Language :: English
Classifier: Operating System :: MacOS :: MacOS X
Classifier: Operating System :: POSIX :: Linux
Classifier: Programming Language :: Python
Classifier: Programming Language :: Python :: 2
Classifier: Programming Language :: Python :: 2.7
Classifier: Programming Language :: Python :: 3
Classifier: Programming Language :: Python :: 3.2
Classifier: Programming Language :: Python :: 3.3
Classifier: Programming Language :: Python :: 3.4
Classifier: Programming Language :: Python :: 3.5
Classifier: Programming Language :: Python :: Implementation :: CPython
Classifier: Programming Language :: Python :: Implementation :: PyPy
Classifier: Topic :: Software Development :: Libraries :: Python Modules
